deepprostate/__init__.py
deepprostate/__main__.py
deepprostate/main.py
deepprostate/adapters/__init__.py
deepprostate/adapters/image_conversion/__init__.py
deepprostate/adapters/image_conversion/nifti_converter.py
deepprostate/adapters/image_conversion/temp_file_manager.py
deepprostate/core/__init__.py
deepprostate/core/domain/__init__.py
deepprostate/core/domain/entities/__init__.py
deepprostate/core/domain/entities/ai_analysis.py
deepprostate/core/domain/entities/analysis_state.py
deepprostate/core/domain/entities/enhanced_medical_image.py
deepprostate/core/domain/entities/medical_dimension_analyzer.py
deepprostate/core/domain/entities/medical_image.py
deepprostate/core/domain/entities/segmentation.py
deepprostate/core/domain/exceptions/__init__.py
deepprostate/core/domain/exceptions/medical_exceptions.py
deepprostate/core/domain/repositories/__init__.py
deepprostate/core/domain/repositories/repositories.py
deepprostate/core/domain/services/__init__.py
deepprostate/core/domain/services/ai_analysis_export_service.py
deepprostate/core/domain/services/ai_analysis_persistence_service.py
deepprostate/core/domain/services/ai_inference_service.py
deepprostate/core/domain/services/ai_model_service.py
deepprostate/core/domain/services/ai_preprocessing_service.py
deepprostate/core/domain/services/analysis_state_machine.py
deepprostate/core/domain/services/analysis_validation_service.py
deepprostate/core/domain/services/batch_operation_service.py
deepprostate/core/domain/services/dynamic_model_config_service.py
deepprostate/core/domain/services/filename_study_grouper.py
deepprostate/core/domain/services/image_rendering_service.py
deepprostate/core/domain/services/image_validation_service.py
deepprostate/core/domain/services/mask_detection_service.py
deepprostate/core/domain/services/medical_image_cache_service.py
deepprostate/core/domain/services/model_metadata_service.py
deepprostate/core/domain/services/multi_view_manager_service.py
deepprostate-1.3.8.dist-info/licenses/LICENSE
deepprostate-1.3.8.dist-info/METADATA
deepprostate-1.3.8.dist-info/WHEEL
deepprostate-1.3.8.dist-info/entry_points.txt
deepprostate-1.3.8.dist-info/top_level.txt
deepprostate-1.3.8.dist-info/RECORD
