Metadata-Version: 2.4
Name: deepprostate
Version: 1.3.8
Summary: AI-Powered Prostate MRI Analysis Platform
Author-email: Ronald Marca <rnldmarca@gmail.com>
Maintainer-email: Ronald Marca <rnldmarca@gmail.com>
License: Medical Research License
Project-URL: Homepage, https://github.com/Marquita-oss/DeepProstate
Project-URL: Documentation, https://github.com/Marquita-oss/DeepProstate#readme
Project-URL: Repository, https://github.com/Marquita-oss/DeepProstate
Project-URL: Issues, https://github.com/Marquita-oss/DeepProstate/issues
Keywords: medical-imaging,ai,deep-learning,prostate-cancer,nnunet,dicom,medical-ai,segmentation,mri-analysis
Classifier: Development Status :: 4 - Beta
Classifier: Intended Audience :: Healthcare Industry
Classifier: Intended Audience :: Science/Research
Classifier: Topic :: Scientific/Engineering :: Medical Science Apps.
Classifier: Topic :: Scientific/Engineering :: Artificial Intelligence
Classifier: Topic :: Scientific/Engineering :: Image Recognition
Classifier: License :: Other/Proprietary License
Classifier: Programming Language :: Python :: 3
Classifier: Programming Language :: Python :: 3.8
Classifier: Programming Language :: Python :: 3.9
Classifier: Programming Language :: Python :: 3.10
Classifier: Programming Language :: Python :: 3.11
Classifier: Programming Language :: Python :: 3.12
Classifier: Operating System :: OS Independent
Classifier: Environment :: X11 Applications :: Qt
Requires-Python: >=3.8
License-File: LICENSE
Requires-Dist: PyQt6>=6.4.0
Requires-Dist: PyQt6-Qt6>=6.4.0
Requires-Dist: pyqtdarktheme>=0.1.7
Requires-Dist: numpy<2.0.0,>=1.21.0
Requires-Dist: scipy>=1.7.0
Requires-Dist: pydicom>=2.3.0
Requires-Dist: nibabel>=4.0.0
Requires-Dist: SimpleITK>=2.2.0
Requires-Dist: scikit-image>=0.19.0
Requires-Dist: Pillow>=9.0.0
Requires-Dist: psutil>=5.9.0
Requires-Dist: torch>=2.0.0
Requires-Dist: torchvision>=0.15.0
Requires-Dist: vtk>=9.2.0
Requires-Dist: h5py>=3.7.0
Requires-Dist: python-dotenv>=0.20.0
Requires-Dist: python-dateutil>=2.8.0
Requires-Dist: PyYAML>=6.0
Provides-Extra: dev
Requires-Dist: pytest>=7.0.0; extra == "dev"
Requires-Dist: pytest-cov>=3.0.0; extra == "dev"
Requires-Dist: pytest-qt>=4.0.0; extra == "dev"
Requires-Dist: pylint>=2.15.0; extra == "dev"
Requires-Dist: black>=22.0.0; extra == "dev"
Requires-Dist: mypy>=0.990; extra == "dev"
Provides-Extra: docs
Requires-Dist: sphinx>=4.5.0; extra == "docs"
Requires-Dist: sphinx-rtd-theme>=1.0.0; extra == "docs"
Dynamic: license-file
